{
	"credit": "Made with Blockbench",
	"texture_size": [32, 32],
	"textures": {
		"0": "portalmod:turret/turret_body",
		"particle": "portalmod:turret/turret_body"
	},
	"elements": [
		{
			"from": [3.75, 8.75, 5.75],
			"to": [3.75, 19.25, 10.25],
			"rotation": {"angle": 0, "axis": "y", "origin": [5, 13.71429, 8.14286]},
			"faces": {
				"north": {"uv": [5, 10.5, 6, 15.5], "texture": "#0"},
				"east": {"uv": [10, 0, 12, 5], "texture": "#0"},
				"south": {"uv": [6, 10.5, 7, 15.5], "texture": "#0"},
				"west": {"uv": [10, 0, 12, 5], "texture": "#0"},
				"up": {"uv": [2.5, 13, 1.5, 11], "texture": "#0"},
				"down": {"uv": [13, 0, 12, 2], "texture": "#0"}
			}
		},
		{
			"from": [3.75, 8.75, 5.75],
			"to": [6.25, 19.25, 5.75],
			"rotation": {"angle": 0, "axis": "y", "origin": [5, 13.71429, 8.14286]},
			"faces": {
				"north": {"uv": [5, 10.5, 6, 15.5], "texture": "#0"},
				"east": {"uv": [10, 10, 12, 15], "texture": "#0"},
				"south": {"uv": [6, 10.5, 7, 15.5], "texture": "#0"},
				"west": {"uv": [10, 0, 12, 5], "texture": "#0"},
				"up": {"uv": [2.5, 13, 1.5, 11], "texture": "#0"},
				"down": {"uv": [13, 0, 12, 2], "texture": "#0"}
			}
		},
		{
			"from": [6, 12, 8],
			"to": [8, 14, 9],
			"rotation": {"angle": 0, "axis": "y", "origin": [5, 13.71429, 8.14286]},
			"faces": {
				"north": {"uv": [12, 4, 12.5, 5], "texture": "#0"},
				"east": {"uv": [8.5, 12.5, 9, 13.5], "texture": "#0"},
				"south": {"uv": [9, 12.5, 9.5, 13.5], "texture": "#0"},
				"west": {"uv": [9.5, 12.5, 10, 13.5], "texture": "#0"},
				"up": {"uv": [12.5, 12, 12, 11.5], "texture": "#0"},
				"down": {"uv": [13, 2, 12.5, 2.5], "texture": "#0"}
			}
		},
		{
			"from": [3.75, 8.75, 5.75],
			"to": [6.25, 8.75, 10.25],
			"rotation": {"angle": 0, "axis": "y", "origin": [5, 13.71429, 8.14286]},
			"faces": {
				"north": {"uv": [5, 10.5, 6, 15.5], "texture": "#0"},
				"east": {"uv": [10, 10, 12, 15], "texture": "#0"},
				"south": {"uv": [6, 10.5, 7, 15.5], "texture": "#0"},
				"west": {"uv": [10, 0, 12, 5], "texture": "#0"},
				"up": {"uv": [2.5, 13, 1.5, 11], "texture": "#0"},
				"down": {"uv": [13, 0, 12, 2], "texture": "#0"}
			}
		},
		{
			"from": [3.75, 19.25, 5.75],
			"to": [6.25, 19.25, 10.25],
			"rotation": {"angle": 0, "axis": "y", "origin": [5, 13.71429, 8.14286]},
			"faces": {
				"north": {"uv": [5, 10.5, 6, 15.5], "texture": "#0"},
				"east": {"uv": [10, 10, 12, 15], "texture": "#0"},
				"south": {"uv": [6, 10.5, 7, 15.5], "texture": "#0"},
				"west": {"uv": [10, 0, 12, 5], "texture": "#0"},
				"up": {"uv": [2.5, 13, 1.5, 11], "texture": "#0"},
				"down": {"uv": [13, 0, 12, 2], "texture": "#0"}
			}
		},
		{
			"from": [3.75, 8.75, 10.25],
			"to": [6.25, 19.25, 10.25],
			"rotation": {"angle": 0, "axis": "y", "origin": [5, 13.71429, 8.14286]},
			"faces": {
				"north": {"uv": [5, 10.5, 6, 15.5], "texture": "#0"},
				"east": {"uv": [10, 10, 12, 15], "texture": "#0"},
				"south": {"uv": [6, 10.5, 7, 15.5], "texture": "#0"},
				"west": {"uv": [10, 0, 12, 5], "texture": "#0"},
				"up": {"uv": [2.5, 13, 1.5, 11], "texture": "#0"},
				"down": {"uv": [13, 0, 12, 2], "texture": "#0"}
			}
		},
		{
			"from": [5, 11, 7],
			"to": [6, 15, 10],
			"rotation": {"angle": 0, "axis": "y", "origin": [5, 13.71429, 8.14286]},
			"faces": {
				"north": {"uv": [7, 10.5, 7.5, 12.5], "texture": "#0"},
				"east": {"uv": [0, 11, 1.5, 13], "texture": "#0"},
				"south": {"uv": [12, 2, 12.5, 4], "texture": "#0"},
				"west": {"uv": [12, 12, 13.5, 14], "texture": "#0"},
				"up": {"uv": [8, 14, 7.5, 12.5], "texture": "#0"},
				"down": {"uv": [8.5, 12.5, 8, 14], "texture": "#0"}
			}
		}
	],
	"display": {
		"thirdperson_righthand": {
			"translation": [1.6, 1.6, 1.6]
		},
		"head": {
			"translation": [0, -30, 0],
			"scale": [1.6, 1.6, 1.6]
		}
	},
	"groups": [
		{
			"name": "group",
			"origin": [10.5, 8, 6],
			"color": 0,
			"children": [0, 1, 2, 3, 4, 5, 6]
		}
	]
}